{
	"name": "Snowflake_FACT_EPISODES",
	"properties": {
		"linkedServiceName": {
			"referenceName": "IMDb_Project_ls",
			"type": "LinkedServiceReference"
		},
		"annotations": [],
		"type": "SnowflakeV2Table",
		"schema": [
			{
				"name": "EPISODE_SK",
				"type": "NUMBER",
				"precision": 20,
				"scale": 0
			},
			{
				"name": "SEASON_NUMBER",
				"type": "NUMBER",
				"precision": 38,
				"scale": 0
			},
			{
				"name": "EPISODE_NUMBER",
				"type": "NUMBER",
				"precision": 38,
				"scale": 0
			},
			{
				"name": "NUM_EPISODES",
				"type": "NUMBER",
				"precision": 38,
				"scale": 0
			},
			{
				"name": "TITLE_SK",
				"type": "NUMBER",
				"precision": 20,
				"scale": 0
			},
			{
				"name": "PARENT_TITLE_SK",
				"type": "NUMBER",
				"precision": 20,
				"scale": 0
			},
			{
				"name": "JOB_ID",
				"type": "VARCHAR"
			},
			{
				"name": "LOAD_DT",
				"type": "DATE"
			}
		],
		"typeProperties": {
			"schema": "GROUP_6_MIDTERM_PROJECT_EDW",
			"table": "FACT_EPISODES"
		}
	}
}